{
  "manifest": {
    "publishingInformation": {
      "locales": {
        "en-IN": {
          "name": "Meal Planner",
          "summary": "Meal Planner helps you plan meals for your household.",
          "description": "You can ask Meal Planner to set your meal, or just say what do I cook for dinner.",
          "examplePhrases": [
            "Alexa open meal planner",
            "what do I cook for dinner",
            "give me a breakfast suggestion"
          ],
          "keywords": []
        },
        "en-US": {
          "name": "Meal Planner",
          "summary": "Meal Planner helps you plan meals for your household.",
          "description": "You can ask Meal Planner to set your meal, or just say what do I cook for dinner.",
          "examplePhrases": [
            "Alexa open meal planner",
            "what do I cook for dinner",
            "give me a breakfast suggestion"
          ],
          "keywords": []
        },
        "en-GB": {
          "name": "Meal Planner",
          "summary": "Meal Planner helps you plan meals for your household.",
          "description": "You can ask Meal Planner to set your meal, or just say what do I cook for dinner.",
          "examplePhrases": [
            "Alexa open meal planner",
            "what do I cook for dinner",
            "give me a breakfast suggestion"
          ],
          "keywords": []
        },
        "en-AU": {
          "name": "Meal Planner",
          "summary": "Meal Planner helps you plan meals for your household.",
          "description": "You can ask Meal Planner to set your meal, or just say what do I cook for dinner.",
          "examplePhrases": [
            "Alexa open meal planner",
            "what do I cook for dinner",
            "give me a breakfast suggestion"
          ],
          "keywords": []
        },
        "en-CA": {
          "name": "Meal Planner",
          "summary": "Meal Planner helps you plan meals for your household.",
          "description": "You can ask Meal Planner to set your meal, or just say what do I cook for dinner.",
          "examplePhrases": [
            "Alexa open meal planner",
            "what do I cook for dinner",
            "give me a breakfast suggestion"
          ],
          "keywords": []
        }
      },
      "isAvailableWorldwide": true,
      "testingInstructions": "Sample Testing Instructions.",
      "category": "KNOWLEDGE_AND_TRIVIA",
      "distributionCountries": []
    },
    "apis": {
      "custom": {
        "endpoint": {
          "uri": "arn:aws:lambda:us-east-1:583459595861:function:ask-mealplanner-default-default-1599374973993"
        }
      }
    },
    "manifestVersion": "1.0"
  }
}